paper_model/__init__.py
paper_model/config_parser.py
paper_model/manager.py
paper_model/run_pipeline.py
paper_model/evaluation/__init__.py
paper_model/evaluation/metrics.py
paper_model/evaluation/reporter.py
paper_model/models/__init__.py
paper_model/models/base.py
paper_model/models/sklearn_model.py
paper_model/models/torch_model.py
paper_model-0.1.1.dist-info/METADATA
paper_model-0.1.1.dist-info/WHEEL
paper_model-0.1.1.dist-info/entry_points.txt
paper_model-0.1.1.dist-info/licenses/LICENSE
paper_model-0.1.1.dist-info/RECORD
