Metadata-Version: 2.4
Name: paper-model
Version: 0.1.1
Summary: A robust backtesting engine for asset-pricing models.
Author-email: Lorenzo Varese <55581163+lorenzovarese@users.noreply.github.com>
License-File: LICENSE
Requires-Python: >=3.11
Requires-Dist: group-lasso>=1.5.0
Requires-Dist: joblib>=1.5.1
Requires-Dist: pandas>=2.2.3
Requires-Dist: polars>=1.30.0
Requires-Dist: pydantic>=2.11.5
Requires-Dist: pyyaml>=6.0.2
Requires-Dist: scikit-learn>=1.7.0
Requires-Dist: torch>=2.7.1
